codegnan_quest/__init__.py
codegnan_quest/quest_engine.py
codegnan_quest/quiz.py
codegnan_quest/resources/coding_questions.json
codegnan_quest/resources/mcqs.json
codegnan_quest-0.1.0.dist-info/licenses/LICENSE
codegnan_quest-0.1.0.dist-info/METADATA
codegnan_quest-0.1.0.dist-info/WHEEL
codegnan_quest-0.1.0.dist-info/top_level.txt
codegnan_quest-0.1.0.dist-info/RECORD
